ethanpolars/__init__.py
ethanpolars/helpers.py
ethanpolars/py.typed
ethanpolars-0.2.0.dist-info/METADATA
ethanpolars-0.2.0.dist-info/WHEEL
ethanpolars-0.2.0.dist-info/RECORD
